samarth/__init__.py
samarth/cvdl.py
samarth-0.0.3.dist-info/METADATA
samarth-0.0.3.dist-info/WHEEL
samarth-0.0.3.dist-info/top_level.txt
samarth-0.0.3.dist-info/RECORD
