Metadata-Version: 2.4
Name: samarth
Version: 0.0.3
Summary: Enjoy my codes!
Author-email: Samarth Patel <samarthnimeshkumarpatel@gmail.com>
Classifier: Programming Language :: Python :: 3
Classifier: License :: OSI Approved :: MIT License
Classifier: Operating System :: OS Independent
Requires-Python: >=3.7
